rtl/alu.v
module alu(
    input [7:0] a,
    input [7:0] b,
    input [2:0] sel,

    output reg [7:0] y,
    output reg zero,
    output reg carry,
    output reg overflow
);

    reg [8:0] temp;

    always @(*) begin

        // Default values
        y = 8'b00000000;
        carry = 1'b0;
        overflow = 1'b0;

        case (sel)

            // ADD
            3'b000: begin
                temp = {1'b0, a} + {1'b0, b};
                y = temp[7:0];
                carry = temp[8];

                overflow = (~(a[7] ^ b[7])) & (a[7] ^ y[7]);
            end

            // SUB
            3'b001: begin
                y = a - b;

                overflow = (a[7] ^ b[7]) & (a[7] ^ y[7]);
            end

            // AND
            3'b010: begin
                y = a & b;
            end

            // OR
            3'b011: begin
                y = a | b;
            end

            // XOR
            3'b100: begin
                y = a ^ b;
            end

            // NOT
            3'b101: begin
                y = ~a;
            end

            // SHIFT LEFT
            3'b110: begin
                y = a << 1;
                carry = a[7];
            end

            // SHIFT RIGHT
            3'b111: begin
                y = a >> 1;
                carry = a[0];
            end

            default: begin
                y = 8'b00000000;
            end

        endcase

        // Zero Flag
        if (y == 8'b00000000)
            zero = 1'b1;
        else
            zero = 1'b0;

    end

endmodule

tb/alu_tb.v
`timescale 1ns/1ps

module alu_tb;

    // Inputs
    reg [7:0] a;
    reg [7:0] b;
    reg [3:0] sel;

    // Outputs
    wire [7:0] y;
    wire zero;
    wire carry;
    wire overflow;

    // =====================================
    // Instantiate ALU
    // =====================================
    alu uut (
        .a(a),
        .b(b),
        .sel(sel),
        .y(y),
        .zero(zero),
        .carry(carry),
        .overflow(overflow)
    );

    initial begin

        // Generate waveform
        $dumpfile("alu.vcd");
        $dumpvars(0, alu_tb);

        // =====================================
        // DAY 1: BASIC OPERATIONS
        // =====================================

        // ADD: 10 + 5 = 15
        a = 8'd10;
        b = 8'd5;
        sel = 4'b0000;
        #100;

        // SUB: 10 - 5 = 5
        sel = 4'b0001;
        #100;

        // AND
        sel = 4'b0010;
        #100;

        // OR
        sel = 4'b0011;
        #100;

        // =====================================
        // DAY 2: XOR AND NOT
        // =====================================

        // XOR
        sel = 4'b0100;
        #100;

        // NOT A
        sel = 4'b0101;
        #100;

        // =====================================
        // DAY 3: FLAG TESTS
        // =====================================

        // ZERO FLAG: 5 - 5 = 0
        a = 8'd5;
        b = 8'd5;
        sel = 4'b0001;
        #100;

        // CARRY FLAG: 255 + 1 = 256
        a = 8'd255;
        b = 8'd1;
        sel = 4'b0000;
        #100;

        // OVERFLOW FLAG: 127 + 1
        a = 8'd127;
        b = 8'd1;
        sel = 4'b0000;
        #100;

        // =====================================
        // DAY 4: SHIFT OPERATIONS
        // =====================================

        // SHIFT LEFT
        // 10000001 << 1 = 00000010
        // Carry = 1
        a = 8'b10000001;
        b = 8'd0;
        sel = 4'b0110;
        #100;

        // SHIFT RIGHT
        // 10000001 >> 1 = 01000000
        // Carry = 1
        sel = 4'b0111;
        #100;

        // =====================================
        // DAY 5: INCREMENT OPERATION
        // =====================================

        // 10 + 1 = 11
        a = 8'd10;
        b = 8'd0;
        sel = 4'b1000;
        #100;

        // Increment carry test
        // 255 + 1 = 256
        // Result = 0, Carry = 1
        a = 8'd255;
        sel = 4'b1000;
        #100;

        // Increment overflow test
        // 127 + 1 = -128 (signed)
        a = 8'd127;
        sel = 4'b1000;
        #100;

        // Finish simulation
        $finish;

    end

endmodule

alu.vcd
$date
	Sun Aug 23 23:55:11 2026
$end
$version
	ModelSim Version 10.5b
$end
$timescale
	1ps
$end

$scope module alu_tb $end
$var reg 8 ! a [7:0] $end
$var reg 8 " b [7:0] $end
$var reg 4 # sel [3:0] $end
$var wire 1 $ y [7] $end
$var wire 1 % y [6] $end
$var wire 1 & y [5] $end
$var wire 1 ' y [4] $end
$var wire 1 ( y [3] $end
$var wire 1 ) y [2] $end
$var wire 1 * y [1] $end
$var wire 1 + y [0] $end
$var wire 1 , zero $end
$var wire 1 - carry $end
$var wire 1 . overflow $end

$scope module uut $end
$var wire 1 / a [7] $end
$var wire 1 0 a [6] $end
$var wire 1 1 a [5] $end
$var wire 1 2 a [4] $end
$var wire 1 3 a [3] $end
$var wire 1 4 a [2] $end
$var wire 1 5 a [1] $end
$var wire 1 6 a [0] $end
$var wire 1 7 b [7] $end
$var wire 1 8 b [6] $end
$var wire 1 9 b [5] $end
$var wire 1 : b [4] $end
$var wire 1 ; b [3] $end
$var wire 1 < b [2] $end
$var wire 1 = b [1] $end
$var wire 1 > b [0] $end
$var wire 1 ? sel [3] $end
$var wire 1 @ sel [2] $end
$var wire 1 A sel [1] $end
$var wire 1 B sel [0] $end
$var reg 8 C y [7:0] $end
$var reg 1 D zero $end
$var reg 1 E carry $end
$var reg 1 F overflow $end
$var reg 9 G temp [8:0] $end
$upscope $end
$upscope $end
$enddefinitions $end
#0
$dumpvars
b1010 !
b101 "
b0 #
b1111 C
0D
0E
0F
b1111 G
1+
1*
1)
1(
0'
0&
0%
0$
0,
0-
0.
0B
0A
0@
0?
1>
0=
1<
0;
0:
09
08
07
06
15
04
13
02
01
00
0/
$end
#100000
b1 #
1B
b0 C
b0 G
b101 C
0*
0(
#200000
b10 #
0B
1A
b0 C
1D
0+
0)
1,
#300000
b11 #
1B
b1111 C
0D
1+
1*
1)
1(
0,
#400000
b100 #
0B
0A
1@
b0 C
b1111 C
#500000
b101 #
1B
b0 C
b11110101 C
0*
0(
1'
1&
1%
1$
#600000
b101 !
b1 #
0@
16
05
14
03
b0 C
1D
0+
0)
0'
0&
0%
0$
1,
#700000
b11111111 !
b1 "
b0 #
0B
0<
15
13
12
11
10
1/
b100000000 G
1E
1-
#800000
b1111111 !
0/
0E
b0 G
b10000000 G
b10000000 C
1F
0D
0-
1$
1.
0,
#900000
b10000001 !
b0 "
b110 #
1A
1@
0>
05
04
03
02
01
00
1/
b0 C
0F
b0 G
b10 C
1E
1*
0$
0.
1-
#1000000
b111 #
1B
b0 C
0E
b1000000 C
1E
0*
1%
#1100000
b1010 !
b1000 #
0B
0A
0@
1?
06
15
13
0/
b0 C
0E
b1011 G
b1011 C
1+
1*
1(
0%
0-
#1200000
b11111111 !
16
14
12
11
10
1/
b0 C
b0 G
b100000000 G
1E
1D
0+
0*
0(
1-
1,
#1300000
b1111111 !
0/
0E
b0 G
b10000000 G
b10000000 C
1F
0D
0-
1$
1.
0,
