rtl/alu.v
module alu(
    input [7:0] a,
    input [7:0] b,
    input [2:0] sel,

    output reg [7:0] y,
    output reg zero,
    output reg carry,
    output reg overflow
);

    reg [8:0] temp;

    always @(*) begin

        // Default values
        y = 8'b00000000;
        carry = 1'b0;
        overflow = 1'b0;

        case (sel)

            // ADD
            3'b000: begin
                temp = {1'b0, a} + {1'b0, b};
                y = temp[7:0];
                carry = temp[8];

                overflow = (~(a[7] ^ b[7])) & (a[7] ^ y[7]);
            end

            // SUB
            3'b001: begin
                y = a - b;

                overflow = (a[7] ^ b[7]) & (a[7] ^ y[7]);
            end

            // AND
            3'b010: begin
                y = a & b;
            end

            // OR
            3'b011: begin
                y = a | b;
            end

            // XOR
            3'b100: begin
                y = a ^ b;
            end

            // NOT
            3'b101: begin
                y = ~a;
            end

            // SHIFT LEFT
            3'b110: begin
                y = a << 1;
                carry = a[7];
            end

            // SHIFT RIGHT
            3'b111: begin
                y = a >> 1;
                carry = a[0];
            end

            default: begin
                y = 8'b00000000;
            end

        endcase

        // Zero Flag
        if (y == 8'b00000000)
            zero = 1'b1;
        else
            zero = 1'b0;

    end

endmodule

tb/alu_tb.v
`timescale 1ns/1ps

module alu_tb;

    reg [7:0] a;
    reg [7:0] b;
    reg [2:0] sel;

    wire [7:0] y;
    wire zero;
    wire carry;
    wire overflow;

    alu uut (
        .a(a),
        .b(b),
        .sel(sel),
        .y(y),
        .zero(zero),
        .carry(carry),
        .overflow(overflow)
    );

    initial begin

        $dumpfile("alu.vcd");
        $dumpvars(0, alu_tb);

        // =====================
        // DAY 1 OPERATIONS
        // =====================

        // ADD: 10 + 5 = 15
        a = 8'd10;
        b = 8'd5;
        sel = 3'b000;
        #100;

        // SUB: 10 - 5 = 5
        sel = 3'b001;
        #100;

        // AND
        sel = 3'b010;
        #100;

        // OR
        sel = 3'b011;
        #100;

        // =====================
        // DAY 2 OPERATIONS
        // =====================

        // XOR
        sel = 3'b100;
        #100;

        // NOT A
        sel = 3'b101;
        #100;

        // =====================
        // DAY 3 FLAG TESTS
        // =====================

        // ZERO FLAG: 5 - 5 = 0
        a = 8'd5;
        b = 8'd5;
        sel = 3'b001;
        #100;

        // CARRY FLAG: 255 + 1
        a = 8'd255;
        b = 8'd1;
        sel = 3'b000;
        #100;

        // OVERFLOW FLAG: 127 + 1
        a = 8'd127;
        b = 8'd1;
        sel = 3'b000;
        #100;

        // =====================
        // DAY 4 SHIFT OPERATIONS
        // =====================

        // SHIFT LEFT
        // 10000001 << 1 = 00000010
        // Carry = 1
        a = 8'b10000001;
        b = 8'd0;
        sel = 3'b110;
        #100;

        // SHIFT RIGHT
        // 10000001 >> 1 = 01000000
        // Carry = 1
        sel = 3'b111;
        #100;

        $finish;

    end

endmodule

alu.vcd
$date
	Sat Aug 22 10:25:24 2026
$end
$version
	ModelSim Version 10.5b
$end
$timescale
	1ps
$end

$scope module alu_tb $end
$var reg 8 ! a [7:0] $end
$var reg 8 " b [7:0] $end
$var reg 3 # sel [2:0] $end
$var wire 1 $ y [7] $end
$var wire 1 % y [6] $end
$var wire 1 & y [5] $end
$var wire 1 ' y [4] $end
$var wire 1 ( y [3] $end
$var wire 1 ) y [2] $end
$var wire 1 * y [1] $end
$var wire 1 + y [0] $end
$var wire 1 , zero $end
$var wire 1 - carry $end
$var wire 1 . overflow $end

$scope module uut $end
$var wire 1 / a [7] $end
$var wire 1 0 a [6] $end
$var wire 1 1 a [5] $end
$var wire 1 2 a [4] $end
$var wire 1 3 a [3] $end
$var wire 1 4 a [2] $end
$var wire 1 5 a [1] $end
$var wire 1 6 a [0] $end
$var wire 1 7 b [7] $end
$var wire 1 8 b [6] $end
$var wire 1 9 b [5] $end
$var wire 1 : b [4] $end
$var wire 1 ; b [3] $end
$var wire 1 < b [2] $end
$var wire 1 = b [1] $end
$var wire 1 > b [0] $end
$var wire 1 ? sel [2] $end
$var wire 1 @ sel [1] $end
$var wire 1 A sel [0] $end
$var reg 8 B y [7:0] $end
$var reg 1 C zero $end
$var reg 1 D carry $end
$var reg 1 E overflow $end
$var reg 9 F temp [8:0] $end
$upscope $end
$upscope $end
$enddefinitions $end
#0
$dumpvars
b1010 !
b101 "
b0 #
b1111 B
0C
0D
0E
b1111 F
1+
1*
1)
1(
0'
0&
0%
0$
0,
0-
0.
0A
0@
0?
1>
0=
1<
0;
0:
09
08
07
06
15
04
13
02
01
00
0/
$end
#10000
b1 #
1A
b0 B
b101 B
0*
0(
#20000
b10 #
0A
1@
b0 B
1C
0+
0)
1,
#30000
b11 #
1A
b1111 B
0C
1+
1*
1)
1(
0,
#40000
b100 #
0A
0@
1?
b0 B
b1111 B
#50000
b101 #
1A
b0 B
b11110101 B
0*
0(
1'
1&
1%
1$
#60000
b101 !
b1 #
0?
16
05
14
03
b0 B
1C
0+
0)
0'
0&
0%
0$
1,
#70000
b11111111 !
b1 "
b0 #
0A
0<
15
13
12
11
10
1/
b100000000 F
1D
1-
#80000
b1111111 !
0/
0D
b10000000 F
b10000000 B
1E
0C
0-
1$
1.
0,
