rtl/instruction_memory.v
`timescale 1ns/1ps

module instruction_memory (
    input  wire [31:0] address,
    output reg  [31:0] instruction
);

    reg [31:0] memory [0:15];

    initial begin

        // Example instructions
        memory[0]  = 32'h00000001;
        memory[1]  = 32'h00000002;
        memory[2]  = 32'h00000003;
        memory[3]  = 32'h00000004;
        memory[4]  = 32'h00000005;
        memory[5]  = 32'h00000006;
        memory[6]  = 32'h00000007;
        memory[7]  = 32'h00000008;
        memory[8]  = 32'h00000009;
        memory[9]  = 32'h0000000A;
        memory[10] = 32'h0000000B;
        memory[11] = 32'h0000000C;
        memory[12] = 32'h0000000D;
        memory[13] = 32'h0000000E;
        memory[14] = 32'h0000000F;
        memory[15] = 32'h00000010;

    end

    always @(*) begin

        // Address is byte address.
        // Divide by 4 to get instruction index.

        if (address < 32'd64)
            instruction = memory[address[5:2]];
        else
            instruction = 32'h00000000;

    end

endmodule

tb/instruction_memory_tb.v
`timescale 1ns/1ps

module instruction_memory_tb;

    reg [31:0] address;
    wire [31:0] instruction;

    // Instantiate Instruction Memory
    instruction_memory uut (
        .address(address),
        .instruction(instruction)
    );

    initial begin

        // Create waveform
        $dumpfile("instruction_memory_waveform.vcd");
        $dumpvars(0, instruction_memory_tb);

        $monitor(
            "Time=%0t | Address=%d | Instruction=%h",
            $time,
            address,
            instruction
        );

        // =========================
        // Instruction 0
        // =========================

        address = 32'd0;
        #10;

        // =========================
        // Instruction 1
        // =========================

        address = 32'd4;
        #10;

        // =========================
        // Instruction 2
        // =========================

        address = 32'd8;
        #10;

        // =========================
        // Instruction 3
        // =========================

        address = 32'd12;
        #10;

        // =========================
        // Instruction 4
        // =========================

        address = 32'd16;
        #10;

        // =========================
        // Instruction 5
        // =========================

        address = 32'd20;
        #10;

        // =========================
        // Instruction 10
        // =========================

        address = 32'd40;
        #10;

        // =========================
        // Invalid address
        // =========================

        address = 32'd100;
        #10;

        $finish;

    end

endmodule

instruction_memory_waveform.vcd
$date
	Sun Aug 30 10:29:36 2026
$end
$version
	ModelSim Version 10.5b
$end
$timescale
	1ps
$end

$scope module instruction_memory_tb $end
$var reg 32 ! address [31:0] $end
$var wire 1 " instruction [31] $end
$var wire 1 # instruction [30] $end
$var wire 1 $ instruction [29] $end
$var wire 1 % instruction [28] $end
$var wire 1 & instruction [27] $end
$var wire 1 ' instruction [26] $end
$var wire 1 ( instruction [25] $end
$var wire 1 ) instruction [24] $end
$var wire 1 * instruction [23] $end
$var wire 1 + instruction [22] $end
$var wire 1 , instruction [21] $end
$var wire 1 - instruction [20] $end
$var wire 1 . instruction [19] $end
$var wire 1 / instruction [18] $end
$var wire 1 0 instruction [17] $end
$var wire 1 1 instruction [16] $end
$var wire 1 2 instruction [15] $end
$var wire 1 3 instruction [14] $end
$var wire 1 4 instruction [13] $end
$var wire 1 5 instruction [12] $end
$var wire 1 6 instruction [11] $end
$var wire 1 7 instruction [10] $end
$var wire 1 8 instruction [9] $end
$var wire 1 9 instruction [8] $end
$var wire 1 : instruction [7] $end
$var wire 1 ; instruction [6] $end
$var wire 1 < instruction [5] $end
$var wire 1 = instruction [4] $end
$var wire 1 > instruction [3] $end
$var wire 1 ? instruction [2] $end
$var wire 1 @ instruction [1] $end
$var wire 1 A instruction [0] $end

$scope module uut $end
$var wire 1 B address [31] $end
$var wire 1 C address [30] $end
$var wire 1 D address [29] $end
$var wire 1 E address [28] $end
$var wire 1 F address [27] $end
$var wire 1 G address [26] $end
$var wire 1 H address [25] $end
$var wire 1 I address [24] $end
$var wire 1 J address [23] $end
$var wire 1 K address [22] $end
$var wire 1 L address [21] $end
$var wire 1 M address [20] $end
$var wire 1 N address [19] $end
$var wire 1 O address [18] $end
$var wire 1 P address [17] $end
$var wire 1 Q address [16] $end
$var wire 1 R address [15] $end
$var wire 1 S address [14] $end
$var wire 1 T address [13] $end
$var wire 1 U address [12] $end
$var wire 1 V address [11] $end
$var wire 1 W address [10] $end
$var wire 1 X address [9] $end
$var wire 1 Y address [8] $end
$var wire 1 Z address [7] $end
$var wire 1 [ address [6] $end
$var wire 1 \ address [5] $end
$var wire 1 ] address [4] $end
$var wire 1 ^ address [3] $end
$var wire 1 _ address [2] $end
$var wire 1 ` address [1] $end
$var wire 1 a address [0] $end
$var reg 32 b instruction [31:0] $end
$upscope $end
$upscope $end
$enddefinitions $end
#0
$dumpvars
b0 !
b1 b
1A
0@
0?
0>
0=
0<
0;
0:
09
08
07
06
05
04
03
02
01
00
0/
0.
0-
0,
0+
0*
0)
0(
0'
0&
0%
0$
0#
0"
0a
0`
0_
0^
0]
0\
0[
0Z
0Y
0X
0W
0V
0U
0T
0S
0R
0Q
0P
0O
0N
0M
0L
0K
0J
0I
0H
0G
0F
0E
0D
0C
0B
$end
#10000
b100 !
1_
b10 b
0A
1@
#20000
b1000 !
0_
1^
b11 b
1A
#30000
b1100 !
1_
b100 b
0A
0@
1?
#40000
b10000 !
0_
0^
1]
b101 b
1A
#50000
b10100 !
1_
b110 b
0A
1@
#60000
b101000 !
0_
1^
0]
1\
b1011 b
1A
0?
1>
#70000
b1100100 !
1_
0^
1[
b0 b
0A
0@
0>
