rtl/program_counter.v
`timescale 1ns/1ps

module program_counter (
    input  wire        clk,
    input  wire        reset,
    input  wire        enable,
    input  wire        load,
    input  wire [31:0] load_address,

    output reg  [31:0] pc
);

always @(posedge clk or posedge reset) begin

    if (reset) begin
        pc <= 32'd0;
    end

    else if (load) begin
        pc <= load_address;
    end

    else if (enable) begin
        pc <= pc + 32'd4;
    end

end

endmodule

tb/program_counter_tb.v
`timescale 1ns/1ps

module program_counter_tb;

    reg clk;
    reg reset;
    reg enable;
    reg load;

    reg [31:0] load_address;

    wire [31:0] pc;


    // =====================================
    // Instantiate Program Counter
    // =====================================

    program_counter uut (
        .clk(clk),
        .reset(reset),
        .enable(enable),
        .load(load),
        .load_address(load_address),
        .pc(pc)
    );


    // =====================================
    // Clock Generation
    // =====================================

    initial begin
        clk = 1'b0;

        forever #5 clk = ~clk;
    end


    // =====================================
    // Testbench
    // =====================================

    initial begin

        // Create waveform
        $dumpfile("program_counter_waveform.vcd");
        $dumpvars(0, program_counter_tb);
$monitor(
    "Time=%0t | Reset=%b | Enable=%b | Load=%b | Load_Address=%d | PC=%d",
    $time, reset, enable, load, load_address, pc
);

        // Initial values
        reset = 1'b1;
        enable = 1'b0;
        load = 1'b0;
        load_address = 32'd0;

        #10;


        // =================================
        // Release Reset
        // PC should be 0
        // =================================

        reset = 1'b0;
        enable = 1'b1;

        #10;


        // =================================
        // PC increments
        // 0 -> 4
        // =================================

        #10;


        // =================================
        // PC increments
        // 4 -> 8
        // =================================

        #10;


        // =================================
        // PC increments
        // 8 -> 12
        // =================================

        #10;


        // =================================
        // LOAD ADDRESS
        // PC = 100
        // =================================

        load = 1'b1;
        enable = 1'b0;
        load_address = 32'd100;

        #10;


        // =================================
        // Continue incrementing
        // 100 -> 104
        // =================================

        load = 1'b0;
        enable = 1'b1;

        #10;


        // =================================
        // 104 -> 108
        // =================================

        #10;


        // =================================
        // HOLD PC
        // =================================

        enable = 1'b0;

        #20;


        // =================================
        // RESET
        // PC should return to 0
        // =================================

        reset = 1'b1;

        #10;

        reset = 1'b0;

        #10;


        $finish;

    end

endmodule

program_counter_waveform.vcd
$date
	Sat Aug 29 21:25:37 2026
$end
$version
	ModelSim Version 10.5b
$end
$timescale
	1ps
$end

$scope module program_counter_tb $end
$var reg 1 ! clk $end
$var reg 1 " reset $end
$var reg 1 # enable $end
$var reg 1 $ load $end
$var reg 32 % load_address [31:0] $end
$var wire 1 & pc [31] $end
$var wire 1 ' pc [30] $end
$var wire 1 ( pc [29] $end
$var wire 1 ) pc [28] $end
$var wire 1 * pc [27] $end
$var wire 1 + pc [26] $end
$var wire 1 , pc [25] $end
$var wire 1 - pc [24] $end
$var wire 1 . pc [23] $end
$var wire 1 / pc [22] $end
$var wire 1 0 pc [21] $end
$var wire 1 1 pc [20] $end
$var wire 1 2 pc [19] $end
$var wire 1 3 pc [18] $end
$var wire 1 4 pc [17] $end
$var wire 1 5 pc [16] $end
$var wire 1 6 pc [15] $end
$var wire 1 7 pc [14] $end
$var wire 1 8 pc [13] $end
$var wire 1 9 pc [12] $end
$var wire 1 : pc [11] $end
$var wire 1 ; pc [10] $end
$var wire 1 < pc [9] $end
$var wire 1 = pc [8] $end
$var wire 1 > pc [7] $end
$var wire 1 ? pc [6] $end
$var wire 1 @ pc [5] $end
$var wire 1 A pc [4] $end
$var wire 1 B pc [3] $end
$var wire 1 C pc [2] $end
$var wire 1 D pc [1] $end
$var wire 1 E pc [0] $end

$scope module uut $end
$var wire 1 F clk $end
$var wire 1 G reset $end
$var wire 1 H enable $end
$var wire 1 I load $end
$var wire 1 J load_address [31] $end
$var wire 1 K load_address [30] $end
$var wire 1 L load_address [29] $end
$var wire 1 M load_address [28] $end
$var wire 1 N load_address [27] $end
$var wire 1 O load_address [26] $end
$var wire 1 P load_address [25] $end
$var wire 1 Q load_address [24] $end
$var wire 1 R load_address [23] $end
$var wire 1 S load_address [22] $end
$var wire 1 T load_address [21] $end
$var wire 1 U load_address [20] $end
$var wire 1 V load_address [19] $end
$var wire 1 W load_address [18] $end
$var wire 1 X load_address [17] $end
$var wire 1 Y load_address [16] $end
$var wire 1 Z load_address [15] $end
$var wire 1 [ load_address [14] $end
$var wire 1 \ load_address [13] $end
$var wire 1 ] load_address [12] $end
$var wire 1 ^ load_address [11] $end
$var wire 1 _ load_address [10] $end
$var wire 1 ` load_address [9] $end
$var wire 1 a load_address [8] $end
$var wire 1 b load_address [7] $end
$var wire 1 c load_address [6] $end
$var wire 1 d load_address [5] $end
$var wire 1 e load_address [4] $end
$var wire 1 f load_address [3] $end
$var wire 1 g load_address [2] $end
$var wire 1 h load_address [1] $end
$var wire 1 i load_address [0] $end
$var reg 32 j pc [31:0] $end
$upscope $end
$upscope $end
$enddefinitions $end
#0
$dumpvars
0!
1"
0#
0$
b0 %
b0 j
0E
0D
0C
0B
0A
0@
0?
0>
0=
0<
0;
0:
09
08
07
06
05
04
03
02
01
00
0/
0.
0-
0,
0+
0*
0)
0(
0'
0&
0i
0h
0g
0f
0e
0d
0c
0b
0a
0`
0_
0^
0]
0\
0[
0Z
0Y
0X
0W
0V
0U
0T
0S
0R
0Q
0P
0O
0N
0M
0L
0K
0J
0I
0H
1G
0F
$end
#5000
1!
1F
#10000
0"
1#
0!
1H
0G
0F
#15000
1!
1F
b100 j
1C
#20000
0!
0F
#25000
1!
1F
b1000 j
0C
1B
#30000
0!
0F
#35000
1!
1F
b1100 j
1C
#40000
0!
0F
#45000
1!
1F
b10000 j
0C
0B
1A
#50000
1$
0#
b1100100 %
0!
1I
0H
1g
1d
1c
0F
#55000
1!
1F
b1100100 j
1C
0A
1@
1?
#60000
0$
1#
0!
0I
1H
0F
#65000
1!
1F
b1101000 j
0C
1B
#70000
0!
0F
#75000
1!
1F
b1101100 j
1C
#80000
0#
0!
0H
0F
#85000
1!
1F
#90000
0!
0F
#95000
1!
1F
#100000
1"
0!
1G
0F
b0 j
0C
0B
0@
0?
#105000
1!
1F
#110000
0"
0!
0G
0F
