rtl/register_file.v
`timescale 1ns/1ps

module register_file (
    input wire clk,
    input wire reset,
    input wire we,

    input wire [2:0] write_addr,
    input wire [2:0] read_addr1,
    input wire [2:0] read_addr2,

    input wire [7:0] write_data,

    output wire [7:0] read_data1,
    output wire [7:0] read_data2
);

    // 8 registers, each 8 bits
    reg [7:0] registers [0:7];

    integer i;

    // Write operation
    always @(posedge clk or posedge reset) begin
        if (reset) begin
            for (i = 0; i < 8; i = i + 1) begin
                registers[i] <= 8'b00000000;
            end
        end
        else if (we) begin
            registers[write_addr] <= write_data;
        end
    end

    // Read operation
    assign read_data1 = registers[read_addr1];
    assign read_data2 = registers[read_addr2];

endmodule

tb/register_file_tb.v
`timescale 1ns/1ps

module register_file_tb;

    reg clk;
    reg reset;
    reg we;

    reg [2:0] write_addr;
    reg [2:0] read_addr1;
    reg [2:0] read_addr2;

    reg [7:0] write_data;

    wire [7:0] read_data1;
    wire [7:0] read_data2;


    // Instantiate Register File
    register_file uut (
        .clk(clk),
        .reset(reset),
        .we(we),

        .write_addr(write_addr),
        .read_addr1(read_addr1),
        .read_addr2(read_addr2),

        .write_data(write_data),

        .read_data1(read_data1),
        .read_data2(read_data2)
    );


    // Clock generation
    initial begin
        clk = 0;

        forever #5 clk = ~clk;
    end


    // Test cases
    initial begin

        // Generate waveform
        $dumpfile("register_file_waveform.vcd");
        $dumpvars(0, register_file_tb);


        // Initial values
        reset = 1;
        we = 0;

        write_addr = 3'b000;
        read_addr1 = 3'b000;
        read_addr2 = 3'b000;

        write_data = 8'b00000000;

        #10;

        // Release reset
        reset = 0;


        // ============================
        // Write 10 into Register R1
        // ============================

        we = 1;
        write_addr = 3'b001;
        write_data = 8'd10;

        #10;


        // ============================
        // Write 20 into Register R2
        // ============================

        write_addr = 3'b010;
        write_data = 8'd20;

        #10;


        // ============================
        // Write 30 into Register R3
        // ============================

        write_addr = 3'b011;
        write_data = 8'd30;

        #10;


        // Disable writing
        we = 0;


        // ============================
        // Read R1 and R2
        // Expected:
        // read_data1 = 10
        // read_data2 = 20
        // ============================

        read_addr1 = 3'b001;
        read_addr2 = 3'b010;

        #10;


        // ============================
        // Read R2 and R3
        // Expected:
        // read_data1 = 20
        // read_data2 = 30
        // ============================

        read_addr1 = 3'b010;
        read_addr2 = 3'b011;

        #10;


        // ============================
        // Read R1 and R3
        // Expected:
        // read_data1 = 10
        // read_data2 = 30
        // ============================

        read_addr1 = 3'b001;
        read_addr2 = 3'b011;

        #20;

        $finish;

    end

endmodule

register_file_waveform.vcd
$date
	Sat Aug 29 21:25:32 2026
$end
$version
	ModelSim Version 10.5b
$end
$timescale
	1ps
$end

$scope module register_file_tb $end
$var reg 1 ! clk $end
$var reg 1 " reset $end
$var reg 1 # we $end
$var reg 3 $ write_addr [2:0] $end
$var reg 3 % read_addr1 [2:0] $end
$var reg 3 & read_addr2 [2:0] $end
$var reg 8 ' write_data [7:0] $end
$var wire 1 ( read_data1 [7] $end
$var wire 1 ) read_data1 [6] $end
$var wire 1 * read_data1 [5] $end
$var wire 1 + read_data1 [4] $end
$var wire 1 , read_data1 [3] $end
$var wire 1 - read_data1 [2] $end
$var wire 1 . read_data1 [1] $end
$var wire 1 / read_data1 [0] $end
$var wire 1 0 read_data2 [7] $end
$var wire 1 1 read_data2 [6] $end
$var wire 1 2 read_data2 [5] $end
$var wire 1 3 read_data2 [4] $end
$var wire 1 4 read_data2 [3] $end
$var wire 1 5 read_data2 [2] $end
$var wire 1 6 read_data2 [1] $end
$var wire 1 7 read_data2 [0] $end

$scope module uut $end
$var wire 1 8 clk $end
$var wire 1 9 reset $end
$var wire 1 : we $end
$var wire 1 ; write_addr [2] $end
$var wire 1 < write_addr [1] $end
$var wire 1 = write_addr [0] $end
$var wire 1 > read_addr1 [2] $end
$var wire 1 ? read_addr1 [1] $end
$var wire 1 @ read_addr1 [0] $end
$var wire 1 A read_addr2 [2] $end
$var wire 1 B read_addr2 [1] $end
$var wire 1 C read_addr2 [0] $end
$var wire 1 D write_data [7] $end
$var wire 1 E write_data [6] $end
$var wire 1 F write_data [5] $end
$var wire 1 G write_data [4] $end
$var wire 1 H write_data [3] $end
$var wire 1 I write_data [2] $end
$var wire 1 J write_data [1] $end
$var wire 1 K write_data [0] $end
$var wire 1 ( read_data1 [7] $end
$var wire 1 ) read_data1 [6] $end
$var wire 1 * read_data1 [5] $end
$var wire 1 + read_data1 [4] $end
$var wire 1 , read_data1 [3] $end
$var wire 1 - read_data1 [2] $end
$var wire 1 . read_data1 [1] $end
$var wire 1 / read_data1 [0] $end
$var wire 1 0 read_data2 [7] $end
$var wire 1 1 read_data2 [6] $end
$var wire 1 2 read_data2 [5] $end
$var wire 1 3 read_data2 [4] $end
$var wire 1 4 read_data2 [3] $end
$var wire 1 5 read_data2 [2] $end
$var wire 1 6 read_data2 [1] $end
$var wire 1 7 read_data2 [0] $end
$var integer 32 L i $end
$upscope $end
$upscope $end
$enddefinitions $end
#0
$dumpvars
0!
1"
0#
b0 $
b0 %
b0 &
b0 '
b1000 L
0/
0.
0-
0,
0+
0*
0)
0(
07
06
05
04
03
02
01
00
0K
0J
0I
0H
0G
0F
0E
0D
0C
0B
0A
0@
0?
0>
0=
0<
0;
0:
19
08
$end
#5000
1!
18
b0 L
b1 L
b10 L
b11 L
b100 L
b101 L
b110 L
b111 L
b1000 L
#10000
0"
1#
b1 $
b1010 '
0!
1:
1J
1H
1=
09
08
#15000
1!
18
#20000
b10 $
b10100 '
0!
0J
1I
0H
1G
0=
1<
08
#25000
1!
18
#30000
b11 $
b11110 '
0!
1J
1H
1=
08
#35000
1!
18
#40000
0#
b1 %
b10 &
0!
0:
1B
1@
1.
1,
15
13
08
#45000
1!
18
#50000
b10 %
b11 &
0!
1C
0@
1?
0.
1-
0,
1+
16
14
08
#55000
1!
18
#60000
b1 %
0!
1@
0?
1.
0-
1,
0+
08
