rtl/alu.v
module alu(
    input [7:0] a,
    input [7:0] b,
    input [3:0] sel,

    output reg [7:0] y,
    output reg zero,
    output reg carry,
    output reg overflow
);

    reg [8:0] temp;

    always @(*) begin

        // Default values
        y = 8'b00000000;
        carry = 1'b0;
        overflow = 1'b0;
        temp = 9'b000000000;

        case (sel)

            // =====================================
            // ADD
            // =====================================
            4'b0000: begin
                temp = {1'b0, a} + {1'b0, b};
                y = temp[7:0];
                carry = temp[8];

                // Signed overflow detection
                overflow = (~(a[7] ^ b[7])) & (a[7] ^ y[7]);
            end

            // =====================================
            // SUBTRACT
            // =====================================
            4'b0001: begin
                y = a - b;

                // Signed overflow detection
                overflow = (a[7] ^ b[7]) & (a[7] ^ y[7]);
            end

            // =====================================
            // AND
            // =====================================
            4'b0010: begin
                y = a & b;
            end

            // =====================================
            // OR
            // =====================================
            4'b0011: begin
                y = a | b;
            end

            // =====================================
            // XOR
            // =====================================
            4'b0100: begin
                y = a ^ b;
            end

            // =====================================
            // NOT
            // =====================================
            4'b0101: begin
                y = ~a;
            end

            // =====================================
            // SHIFT LEFT
            // =====================================
            4'b0110: begin
                y = a << 1;
                carry = a[7];
            end

            // =====================================
            // SHIFT RIGHT
            // =====================================
            4'b0111: begin
                y = a >> 1;
                carry = a[0];
            end

            // =====================================
            // INCREMENT
            // =====================================
            4'b1000: begin
                temp = {1'b0, a} + 9'd1;
                y = temp[7:0];
                carry = temp[8];

                // Overflow: +127 + 1 = -128
                overflow = (~a[7]) & y[7];
            end

            // Default
            default: begin
                y = 8'b00000000;
            end

        endcase

        // =====================================
        // ZERO FLAG
        // =====================================
        if (y == 8'b00000000)
            zero = 1'b1;
        else
            zero = 1'b0;

    end

endmodule

tb/alu_tb.v
`timescale 1ns/1ps

module alu_tb;

    // Inputs
    reg [7:0] a;
    reg [7:0] b;
    reg [3:0] sel;

    // Outputs
    wire [7:0] y;
    wire zero;
    wire carry;
    wire overflow;

    // =====================================
    // Instantiate ALU
    // =====================================
    alu uut (
        .a(a),
        .b(b),
        .sel(sel),
        .y(y),
        .zero(zero),
        .carry(carry),
        .overflow(overflow)
    );

    initial begin

        // Generate waveform
        $dumpfile("alu.vcd");
        $dumpvars(0, alu_tb);

        // =====================================
        // DAY 1: BASIC OPERATIONS
        // =====================================

        // ADD: 10 + 5 = 15
        a = 8'd10;
        b = 8'd5;
        sel = 4'b0000;
        #100;

        // SUB: 10 - 5 = 5
        sel = 4'b0001;
        #100;

        // AND
        sel = 4'b0010;
        #100;

        // OR
        sel = 4'b0011;
        #100;

        // =====================================
        // DAY 2: XOR AND NOT
        // =====================================

        // XOR
        sel = 4'b0100;
        #100;

        // NOT A
        sel = 4'b0101;
        #100;

        // =====================================
        // DAY 3: FLAG TESTS
        // =====================================

        // ZERO FLAG: 5 - 5 = 0
        a = 8'd5;
        b = 8'd5;
        sel = 4'b0001;
        #100;

        // CARRY FLAG: 255 + 1 = 256
        a = 8'd255;
        b = 8'd1;
        sel = 4'b0000;
        #100;

        // OVERFLOW FLAG: 127 + 1
        a = 8'd127;
        b = 8'd1;
        sel = 4'b0000;
        #100;

        // =====================================
        // DAY 4: SHIFT OPERATIONS
        // =====================================

        // SHIFT LEFT
        // 10000001 << 1 = 00000010
        // Carry = 1
        a = 8'b10000001;
        b = 8'd0;
        sel = 4'b0110;
        #100;

        // SHIFT RIGHT
        // 10000001 >> 1 = 01000000
        // Carry = 1
        sel = 4'b0111;
        #100;

        // =====================================
        // DAY 5: INCREMENT OPERATION
        // =====================================

        // 10 + 1 = 11
        a = 8'd10;
        b = 8'd0;
        sel = 4'b1000;
        #100;

        // Increment carry test
        // 255 + 1 = 256
        // Result = 0, Carry = 1
        a = 8'd255;
        sel = 4'b1000;
        #100;

        // Increment overflow test
        // 127 + 1 = -128 (signed)
        a = 8'd127;
        sel = 4'b1000;
        #100;

        // Finish simulation
        $finish;

    end

endmodule

tb/alu.vcd
$date
	Sun Aug 23 09:18:37 2026
$end
$version
	Icarus Verilog
$end
$timescale
	1ps
$end
$scope module alu_tb $end
$var wire 1 ! zero $end
$var wire 8 " y [7:0] $end
$var wire 1 # overflow $end
$var wire 1 $ carry $end
$var reg 8 % a [7:0] $end
$var reg 8 & b [7:0] $end
$var reg 4 ' sel [3:0] $end
$scope module uut $end
$var wire 8 ( a [7:0] $end
$var wire 8 ) b [7:0] $end
$var wire 4 * sel [3:0] $end
$var reg 1 $ carry $end
$var reg 1 # overflow $end
$var reg 9 + temp [8:0] $end
$var reg 8 , y [7:0] $end
$var reg 1 ! zero $end
$upscope $end
$upscope $end
$enddefinitions $end
$comment Show the parameter values. $end
$dumpall
$end
#0
$dumpvars
b1111 ,
b1111 +
b0 *
b101 )
b1010 (
b0 '
b101 &
b1010 %
0$
0#
b1111 "
0!
$end
#100000
b0 +
b101 "
b101 ,
b1 '
b1 *
#200000
1!
b0 "
b0 ,
b10 '
b10 *
#300000
0!
b1111 "
b1111 ,
b11 '
b11 *
#400000
b1111 "
b1111 ,
b100 '
b100 *
#500000
b11110101 "
b11110101 ,
b101 '
b101 *
#600000
1!
b0 "
b0 ,
b1 '
b1 *
b101 %
b101 (
#700000
1$
b100000000 +
b0 '
b0 *
b1 &
b1 )
b11111111 %
b11111111 (
#800000
0!
1#
b10000000 "
b10000000 ,
b10000000 +
0$
b1111111 %
b1111111 (
#900000
1$
b0 +
0#
b10 "
b10 ,
b110 '
b110 *
b0 &
b0 )
b10000001 %
b10000001 (
#1000000
1$
b1000000 "
b1000000 ,
b111 '
b111 *
#1100000
b1011 +
0$
b1011 "
b1011 ,
b1000 '
b1000 *
b1010 %
b1010 (
#1200000
1!
1$
b100000000 +
b0 "
b0 ,
b11111111 %
b11111111 (
#1300000
0!
1#
b10000000 "
b10000000 ,
b10000000 +
0$
b1111111 %
b1111111 (
