rtl/alu.v
module alu(
    input [7:0] a,
    input [7:0] b,
    input [2:0] sel,

    output reg [7:0] y,
    output reg zero,
    output reg carry,
    output reg overflow
);

    reg [8:0] temp;

    always @(*) begin

        // Default values
        y = 8'b00000000;
        carry = 1'b0;
        overflow = 1'b0;

        case (sel)

            // ADD
            3'b000: begin
                temp = {1'b0, a} + {1'b0, b};
                y = temp[7:0];
                carry = temp[8];

                // Signed overflow
                overflow = (~(a[7] ^ b[7])) & (a[7] ^ y[7]);
            end

            // SUB
            3'b001: begin
                y = a - b;

                // Signed overflow
                overflow = (a[7] ^ b[7]) & (a[7] ^ y[7]);
            end

            // AND
            3'b010: begin
                y = a & b;
            end

            // OR
            3'b011: begin
                y = a | b;
            end

            // XOR
            3'b100: begin
                y = a ^ b;
            end

            // NOT A
            3'b101: begin
                y = ~a;
            end

            default: begin
                y = 8'b00000000;
            end

        endcase

        // Zero flag
        if (y == 8'b00000000)
            zero = 1'b1;
        else
            zero = 1'b0;

    end

endmodule

tb/alu_tb.v
`timescale 1ns/1ps

module alu_tb;

    reg [7:0] a;
    reg [7:0] b;
    reg [2:0] sel;

    wire [7:0] y;
    wire zero;
    wire carry;
    wire overflow;

    alu uut (
        .a(a),
        .b(b),
        .sel(sel),
        .y(y),
        .zero(zero),
        .carry(carry),
        .overflow(overflow)
    );

    initial begin

        $dumpfile("alu.vcd");
        $dumpvars(0, alu_tb);

        // =========================
        // Normal operations
        // =========================

        // ADD: 10 + 5 = 15
        a = 8'd10;
        b = 8'd5;
        sel = 3'b000;
        #10;

        // SUB: 10 - 5 = 5
        sel = 3'b001;
        #10;

        // AND
        sel = 3'b010;
        #10;

        // OR
        sel = 3'b011;
        #10;

        // XOR
        sel = 3'b100;
        #10;

        // NOT A
        sel = 3'b101;
        #10;

        // =========================
        // Zero flag test
        // =========================

        // 5 - 5 = 0
        a = 8'd5;
        b = 8'd5;
        sel = 3'b001;
        #10;

        // =========================
        // Carry flag test
        // =========================

        // 255 + 1 = 256
        // Result = 0, Carry = 1
        a = 8'd255;
        b = 8'd1;
        sel = 3'b000;
        #10;

        // =========================
        // Overflow flag test
        // =========================

        // 127 + 1 = 128
        // Signed overflow occurs
        a = 8'd127;
        b = 8'd1;
        sel = 3'b000;
        #10;

        $finish;

    end

endmodule

tb/alu.vcd
$date
	Sat Aug 22 09:58:18 2026
$end
$version
	Icarus Verilog
$end
$timescale
	1ps
$end
$scope module alu_tb $end
$var wire 1 ! zero $end
$var wire 8 " y [7:0] $end
$var wire 1 # overflow $end
$var wire 1 $ carry $end
$var reg 8 % a [7:0] $end
$var reg 8 & b [7:0] $end
$var reg 3 ' sel [2:0] $end
$scope module uut $end
$var wire 8 ( a [7:0] $end
$var wire 8 ) b [7:0] $end
$var wire 3 * sel [2:0] $end
$var reg 1 $ carry $end
$var reg 1 # overflow $end
$var reg 9 + temp [8:0] $end
$var reg 8 , y [7:0] $end
$var reg 1 ! zero $end
$upscope $end
$upscope $end
$enddefinitions $end
$comment Show the parameter values. $end
$dumpall
$end
#0
$dumpvars
b1111 ,
b1111 +
b0 *
b101 )
b1010 (
b0 '
b101 &
b1010 %
0$
0#
b1111 "
0!
$end
#10000
b101 "
b101 ,
b1 '
b1 *
#20000
1!
b0 "
b0 ,
b10 '
b10 *
#30000
0!
b1111 "
b1111 ,
b11 '
b11 *
#40000
b1111 "
b1111 ,
b100 '
b100 *
#50000
b11110101 "
b11110101 ,
b101 '
b101 *
#60000
1!
b0 "
b0 ,
b1 '
b1 *
b101 %
b101 (
#70000
1$
b100000000 +
b0 '
b0 *
b1 &
b1 )
b11111111 %
b11111111 (
#80000
0!
1#
b10000000 "
b10000000 ,
b10000000 +
0$
b1111111 %
b1111111 (
