rtl/alu.v
module alu(
    input [7:0] a,
    input [7:0] b,
    input [3:0] sel,

    output reg [7:0] y,
    output reg zero,
    output reg carry,
    output reg overflow
);

reg [8:0] temp;

always @(*) begin

    // Default values
    y = 8'b00000000;
    carry = 1'b0;
    overflow = 1'b0;
    temp = 9'b000000000;

    case (sel)

        // Basic arithmetic operations
        4'b0000: begin
            temp = a + b;
            y = temp[7:0];
            carry = temp[8];
            overflow = (~(a[7] ^ b[7])) & (y[7] ^ a[7]);
        end

        4'b0001: begin
            y = a - b;
            carry = (a >= b);
            overflow = (a[7] ^ b[7]) & (y[7] ^ a[7]);
        end

        // Basic logic operations
        4'b0010: y = a & b;       // AND

        4'b0011: y = a | b;       // OR

        4'b0100: y = a ^ b;       // XOR

        4'b0101: y = ~a;          // NOT

        // Shift operations
        4'b0110: y = a << 1;      // Shift Left

        4'b0111: y = a >> 1;      // Shift Right

        // Increment
        4'b1000: begin
            temp = a + 1;
            y = temp[7:0];
            carry = temp[8];
        end

        // Comparison operations
        4'b1001: y = (a == b) ? 8'b00000001 : 8'b00000000;

        4'b1010: y = (a > b) ? 8'b00000001 : 8'b00000000;

        4'b1011: y = (a < b) ? 8'b00000001 : 8'b00000000;

        // =========================
        // Day 6 Operations
        // =========================

        4'b1100: y = ~(a & b);    // NAND

        4'b1101: y = ~(a | b);    // NOR

        4'b1110: y = ~(a ^ b);    // XNOR

        default: y = 8'b00000000;

    endcase

    // Zero flag
    if (y == 8'b00000000)
        zero = 1'b1;
    else
        zero = 1'b0;

end

endmodule

tb/alu_tb.v
`timescale 1ns/1ps

module alu_tb;

    // Inputs
    reg [7:0] a;
    reg [7:0] b;
    reg [3:0] sel;

    // Outputs
    wire [7:0] y;
    wire zero;
    wire carry;
    wire overflow;

    // Instantiate ALU
    alu uut (
        .a(a),
        .b(b),
        .sel(sel),
        .y(y),
        .zero(zero),
        .carry(carry),
        .overflow(overflow)
    );

    initial begin

        // Waveform file
        $dumpfile("alu.vcd");
        $dumpvars(0, alu_tb);

        // =========================
        // Day 1: Basic Operations
        // =========================

        // ADD: 10 + 5 = 15
        a = 8'd10;
        b = 8'd5;
        sel = 4'b0000;
        #10;

        // SUB: 10 - 5 = 5
        a = 8'd10;
        b = 8'd5;
        sel = 4'b0001;
        #10;

        // AND
        a = 8'b10101010;
        b = 8'b11001100;
        sel = 4'b0010;
        #10;

        // OR
        sel = 4'b0011;
        #10;

        // XOR
        sel = 4'b0100;
        #10;

        // NOT
        a = 8'b10101010;
        sel = 4'b0101;
        #10;

        // =========================
        // Day 4: Shift Operations
        // =========================

        // Shift Left
        a = 8'b00001111;
        sel = 4'b0110;
        #10;

        // Shift Right
        a = 8'b11110000;
        sel = 4'b0111;
        #10;

        // Increment
        a = 8'd25;
        sel = 4'b1000;
        #10;

        // =========================
        // Day 5: Comparison
        // =========================

        // Equal
        a = 8'd10;
        b = 8'd10;
        sel = 4'b1001;
        #10;

        // Greater Than
        a = 8'd20;
        b = 8'd10;
        sel = 4'b1010;
        #10;

        // Less Than
        a = 8'd5;
        b = 8'd10;
        sel = 4'b1011;
        #10;

        // =========================
        // Day 6: NAND
        // =========================

        a = 8'b10101010;
        b = 8'b11001100;
        sel = 4'b1100;
        #10;

        // NOR
        a = 8'b10101010;
        b = 8'b11001100;
        sel = 4'b1101;
        #10;

        // XNOR
        a = 8'b10101010;
        b = 8'b11001100;
        sel = 4'b1110;
        #10;

        $finish;

    end

endmodule

tb/alu.vcd
$date
	Wed Aug 26 19:09:12 2026
$end
$version
	Icarus Verilog
$end
$timescale
	1ps
$end
$scope module alu_tb $end
$var wire 1 ! zero $end
$var wire 8 " y [7:0] $end
$var wire 1 # overflow $end
$var wire 1 $ carry $end
$var reg 8 % a [7:0] $end
$var reg 8 & b [7:0] $end
$var reg 4 ' sel [3:0] $end
$scope module uut $end
$var wire 8 ( a [7:0] $end
$var wire 8 ) b [7:0] $end
$var wire 4 * sel [3:0] $end
$var reg 1 $ carry $end
$var reg 1 # overflow $end
$var reg 9 + temp [8:0] $end
$var reg 8 , y [7:0] $end
$var reg 1 ! zero $end
$upscope $end
$upscope $end
$enddefinitions $end
$comment Show the parameter values. $end
$dumpall
$end
#0
$dumpvars
b1111 ,
b1111 +
b0 *
b101 )
b1010 (
b0 '
b101 &
b1010 %
0$
0#
b1111 "
0!
$end
#10000
1$
b0 +
b101 "
b101 ,
b1 '
b1 *
#20000
0$
b10001000 "
b10001000 ,
b10 '
b10 *
b11001100 &
b11001100 )
b10101010 %
b10101010 (
#30000
b11101110 "
b11101110 ,
b11 '
b11 *
#40000
b1100110 "
b1100110 ,
b100 '
b100 *
#50000
b1010101 "
b1010101 ,
b101 '
b101 *
#60000
b11110 "
b11110 ,
b110 '
b110 *
b1111 %
b1111 (
#70000
b1111000 "
b1111000 ,
b111 '
b111 *
b11110000 %
b11110000 (
#80000
b11010 +
b11010 "
b11010 ,
b1000 '
b1000 *
b11001 %
b11001 (
#90000
b0 +
b1 "
b1 ,
b1001 '
b1001 *
b1010 &
b1010 )
b1010 %
b1010 (
#100000
b1 "
b1 ,
b1010 '
b1010 *
b10100 %
b10100 (
#110000
b1 "
b1 ,
b1011 '
b1011 *
b101 %
b101 (
#120000
b1110111 "
b1110111 ,
b1100 '
b1100 *
b11001100 &
b11001100 )
b10101010 %
b10101010 (
#130000
b10001 "
b10001 ,
b1101 '
b1101 *
#140000
b10011001 "
b10011001 ,
b1110 '
b1110 *
