rtl/alu.v
module alu(
    input  [7:0] a,
    input  [7:0] b,
    input  [3:0] sel,

    output reg [7:0] y,
    output zero,
    output carry,
    output overflow
);

    reg carry_reg;
    reg overflow_reg;
    reg [8:0] temp;

    always @(*) begin

        y = 8'b00000000;
        carry_reg = 1'b0;
        overflow_reg = 1'b0;
        temp = 9'b000000000;

        case(sel)

            // ADDITION
            4'b0000: begin
                temp = a + b;
                y = temp[7:0];
                carry_reg = temp[8];

                if ((a[7] == b[7]) && (y[7] != a[7]))
                    overflow_reg = 1'b1;
            end

            // SUBTRACTION
            4'b0001: begin
                y = a - b;

                if (a < b)
                    carry_reg = 1'b1;

                if ((a[7] != b[7]) && (y[7] != a[7]))
                    overflow_reg = 1'b1;
            end

            // AND
            4'b0010:
                y = a & b;

            // OR
            4'b0011:
                y = a | b;

            // XOR
            4'b0100:
                y = a ^ b;

            // NOT
            4'b0101:
                y = ~a;

            // SHIFT LEFT
            4'b0110: begin
                y = a << 1;
                carry_reg = a[7];
            end

            // SHIFT RIGHT
            4'b0111: begin
                y = a >> 1;
                carry_reg = a[0];
            end

            // INCREMENT
            4'b1000: begin
                temp = a + 1'b1;
                y = temp[7:0];
                carry_reg = temp[8];
            end

            // LESS THAN
            4'b1001: begin
                if (a < b)
                    y = 8'b00000001;
                else
                    y = 8'b00000000;
            end

            // GREATER THAN
            4'b1010: begin
                if (a > b)
                    y = 8'b00000001;
                else
                    y = 8'b00000000;
            end

            // EQUAL TO
            4'b1011: begin
                if (a == b)
                    y = 8'b00000001;
                else
                    y = 8'b00000000;
            end

            default: begin
                y = 8'b00000000;
            end

        endcase
    end

    assign zero = (y == 8'b00000000);
    assign carry = carry_reg;
    assign overflow = overflow_reg;

endmodule

tb/alu_tb.v
`timescale 1ns/1ps

module alu_tb;

    reg [7:0] a;
    reg [7:0] b;
    reg [3:0] sel;

    wire [7:0] y;
    wire zero;
    wire carry;
    wire overflow;


    // Instantiate ALU

    alu uut (
        .a(a),
        .b(b),
        .sel(sel),
        .y(y),
        .zero(zero),
        .carry(carry),
        .overflow(overflow)
    );


    initial begin

        $dumpfile("alu.vcd");
        $dumpvars(0, alu_tb);


        // =====================================
        // DAY 1 OPERATIONS
        // =====================================

        // ADDITION: 10 + 5 = 15
        a = 8'd10;
        b = 8'd5;
        sel = 4'b0000;
        #10;


        // SUBTRACTION: 10 - 5 = 5
        a = 8'd10;
        b = 8'd5;
        sel = 4'b0001;
        #10;


        // AND
        a = 8'b10101010;
        b = 8'b11001100;
        sel = 4'b0010;
        #10;


        // OR
        a = 8'b10101010;
        b = 8'b11001100;
        sel = 4'b0011;
        #10;


        // =====================================
        // DAY 2 OPERATIONS
        // =====================================

        // XOR
        a = 8'b10101010;
        b = 8'b11001100;
        sel = 4'b0100;
        #10;


        // NOT
        a = 8'b10101010;
        b = 8'b00000000;
        sel = 4'b0101;
        #10;


        // =====================================
        // DAY 4 OPERATIONS
        // =====================================

        // SHIFT LEFT
        a = 8'b00001111;
        b = 8'b00000000;
        sel = 4'b0110;
        #10;


        // SHIFT RIGHT
        a = 8'b11110000;
        b = 8'b00000000;
        sel = 4'b0111;
        #10;


        // INCREMENT
        a = 8'd25;
        b = 8'd0;
        sel = 4'b1000;
        #10;


        // =====================================
        // DAY 5 OPERATIONS
        // =====================================

        // LESS THAN
        // 10 < 20 → y = 1

        a = 8'd10;
        b = 8'd20;
        sel = 4'b1001;
        #10;


        // GREATER THAN
        // 25 > 10 → y = 1

        a = 8'd25;
        b = 8'd10;
        sel = 4'b1010;
        #10;


        // EQUAL TO
        // 15 == 15 → y = 1

        a = 8'd15;
        b = 8'd15;
        sel = 4'b1011;
        #10;


        // LESS THAN FALSE
        // 30 < 10 → y = 0

        a = 8'd30;
        b = 8'd10;
        sel = 4'b1001;
        #10;


        // GREATER THAN FALSE
        // 10 > 20 → y = 0

        a = 8'd10;
        b = 8'd20;
        sel = 4'b1010;
        #10;


        $finish;

    end

endmodule

tb/alu.vcd
$date
	Tue Aug 25 17:42:28 2026
$end
$version
	Icarus Verilog
$end
$timescale
	1ps
$end
$scope module alu_tb $end
$var wire 1 ! zero $end
$var wire 8 " y [7:0] $end
$var wire 1 # overflow $end
$var wire 1 $ carry $end
$var reg 8 % a [7:0] $end
$var reg 8 & b [7:0] $end
$var reg 4 ' sel [3:0] $end
$scope module uut $end
$var wire 8 ( a [7:0] $end
$var wire 8 ) b [7:0] $end
$var wire 1 $ carry $end
$var wire 1 # overflow $end
$var wire 4 * sel [3:0] $end
$var wire 1 ! zero $end
$var reg 1 + carry_reg $end
$var reg 1 , overflow_reg $end
$var reg 9 - temp [8:0] $end
$var reg 8 . y [7:0] $end
$upscope $end
$upscope $end
$enddefinitions $end
$comment Show the parameter values. $end
$dumpall
$end
#0
$dumpvars
b1111 .
b1111 -
0,
0+
b0 *
b101 )
b1010 (
b0 '
b101 &
b1010 %
0$
0#
b1111 "
0!
$end
#10000
b0 -
0!
b101 "
b101 .
b1 '
b1 *
#20000
0!
b10001000 "
b10001000 .
b10 '
b10 *
b11001100 &
b11001100 )
b10101010 %
b10101010 (
#30000
0!
b11101110 "
b11101110 .
b11 '
b11 *
#40000
0!
b1100110 "
b1100110 .
b100 '
b100 *
#50000
0!
b1010101 "
b1010101 .
b101 '
b101 *
b0 &
b0 )
#60000
0!
b11110 "
b11110 .
b110 '
b110 *
b1111 %
b1111 (
#70000
0!
b1111000 "
b1111000 .
b111 '
b111 *
b11110000 %
b11110000 (
#80000
b11010 -
0!
b11010 "
b11010 .
b1000 '
b1000 *
b11001 %
b11001 (
#90000
b0 -
0!
b1 "
b1 .
b1001 '
b1001 *
b10100 &
b10100 )
b1010 %
b1010 (
#100000
0!
b1 "
b1 .
b1010 '
b1010 *
b1010 &
b1010 )
b11001 %
b11001 (
#110000
0!
b1 "
b1 .
b1011 '
b1011 *
b1111 &
b1111 )
b1111 %
b1111 (
#120000
1!
b0 "
b0 .
b1001 '
b1001 *
b1010 &
b1010 )
b11110 %
b11110 (
#130000
b1010 '
b1010 *
b10100 &
b10100 )
b1010 %
b1010 (
