rtl/control_unit.v
`timescale 1ns/1ps

module control_unit (
    input  wire [31:0] instruction,

    output reg [3:0]  alu_sel,
    output reg        reg_write,
    output reg        mem_read,
    output reg        mem_write,
    output reg        alu_src,
    output reg        branch,
    output reg        jump
);

    // Opcode is the upper 6 bits
    wire [5:0] opcode;

    assign opcode = instruction[31:26];

    always @(*) begin

        // Default control signals
        alu_sel   = 4'b0000;
        reg_write = 1'b0;
        mem_read  = 1'b0;
        mem_write = 1'b0;
        alu_src   = 1'b0;
        branch    = 1'b0;
        jump      = 1'b0;

        case (opcode)

            // =================================
            // R-TYPE
            // =================================
            // ALU operation
            6'b000000: begin
                reg_write = 1'b1;
                alu_src   = 1'b0;
            end

            // =================================
            // ADD IMMEDIATE
            // =================================
            6'b001000: begin
                alu_sel   = 4'b0000;
                reg_write = 1'b1;
                alu_src   = 1'b1;
            end

            // =================================
            // SUBTRACT IMMEDIATE
            // =================================
            6'b001001: begin
                alu_sel   = 4'b0001;
                reg_write = 1'b1;
                alu_src   = 1'b1;
            end

            // =================================
            // AND
            // =================================
            6'b001100: begin
                alu_sel   = 4'b0010;
                reg_write = 1'b1;
                alu_src   = 1'b0;
            end

            // =================================
            // OR
            // =================================
            6'b001101: begin
                alu_sel   = 4'b0011;
                reg_write = 1'b1;
                alu_src   = 1'b0;
            end

            // =================================
            // LOAD WORD
            // =================================
            6'b100011: begin
                alu_sel   = 4'b0000;
                reg_write = 1'b1;
                mem_read  = 1'b1;
                alu_src   = 1'b1;
            end

            // =================================
            // STORE WORD
            // =================================
            6'b101011: begin
                alu_sel   = 4'b0000;
                mem_write = 1'b1;
                alu_src   = 1'b1;
            end

            // =================================
            // BRANCH EQUAL
            // =================================
            6'b000100: begin
                alu_sel = 4'b0001;
                branch  = 1'b1;
                alu_src = 1'b0;
            end

            // =================================
            // JUMP
            // =================================
            6'b000010: begin
                jump = 1'b1;
            end

            default: begin
                alu_sel   = 4'b0000;
                reg_write = 1'b0;
                mem_read  = 1'b0;
                mem_write = 1'b0;
                alu_src   = 1'b0;
                branch    = 1'b0;
                jump      = 1'b0;
            end

        endcase

    end

endmodule

tb/control_unit_tb.v
`timescale 1ns/1ps

module control_unit_tb;

    reg [31:0] instruction;

    wire [3:0] alu_sel;
    wire       reg_write;
    wire       mem_read;
    wire       mem_write;
    wire       alu_src;
    wire       branch;
    wire       jump;


    // =====================================
    // Instantiate Control Unit
    // =====================================

    control_unit uut (
        .instruction(instruction),

        .alu_sel(alu_sel),
        .reg_write(reg_write),
        .mem_read(mem_read),
        .mem_write(mem_write),
        .alu_src(alu_src),
        .branch(branch),
        .jump(jump)
    );


    initial begin

        // =================================
        // Waveform
        // =================================

        $dumpfile("control_unit_waveform.vcd");
        $dumpvars(0, control_unit_tb);


        $monitor(
            "Time=%0t | Instruction=%h | ALU_SEL=%b | REG_WRITE=%b | MEM_READ=%b | MEM_WRITE=%b | ALU_SRC=%b | BRANCH=%b | JUMP=%b",
            $time,
            instruction,
            alu_sel,
            reg_write,
            mem_read,
            mem_write,
            alu_src,
            branch,
            jump
        );


        // =================================
        // R-TYPE
        // =================================

        instruction = 32'b000000_00000000000000000000;

        #10;


        // =================================
        // ADD IMMEDIATE
        // =================================

        instruction = 32'b001000_00000000000000000000;

        #10;


        // =================================
        // SUBTRACT IMMEDIATE
        // =================================

        instruction = 32'b001001_00000000000000000000;

        #10;


        // =================================
        // AND
        // =================================

        instruction = 32'b001100_00000000000000000000;

        #10;


        // =================================
        // OR
        // =================================

        instruction = 32'b001101_00000000000000000000;

        #10;


        // =================================
        // LOAD WORD
        // =================================

        instruction = 32'b100011_00000000000000000000;

        #10;


        // =================================
        // STORE WORD
        // =================================

        instruction = 32'b101011_00000000000000000000;

        #10;


        // =================================
        // BRANCH EQUAL
        // =================================

        instruction = 32'b000100_00000000000000000000;

        #10;


        // =================================
        // JUMP
        // =================================

        instruction = 32'b000010_00000000000000000000;

        #10;


        // =================================
        // INVALID OPCODE
        // =================================

        instruction = 32'b111111_00000000000000000000;

        #10;


        $finish;

    end

endmodule

tb/control_unit_waveform.vcd
$date
	Mon Aug 31 19:01:28 2026
$end
$version
	Icarus Verilog
$end
$timescale
	1ps
$end
$scope module control_unit_tb $end
$var wire 1 ! reg_write $end
$var wire 1 " mem_write $end
$var wire 1 # mem_read $end
$var wire 1 $ jump $end
$var wire 1 % branch $end
$var wire 1 & alu_src $end
$var wire 4 ' alu_sel [3:0] $end
$var reg 32 ( instruction [31:0] $end
$scope module uut $end
$var wire 32 ) instruction [31:0] $end
$var wire 6 * opcode [5:0] $end
$var reg 4 + alu_sel [3:0] $end
$var reg 1 & alu_src $end
$var reg 1 % branch $end
$var reg 1 $ jump $end
$var reg 1 # mem_read $end
$var reg 1 " mem_write $end
$var reg 1 ! reg_write $end
$upscope $end
$upscope $end
$enddefinitions $end
$comment Show the parameter values. $end
$dumpall
$end
#0
$dumpvars
b0 +
b0 *
b0 )
b0 (
b0 '
0&
0%
0$
0#
0"
1!
$end
#10000
b100000000000000000000000 (
b100000000000000000000000 )
#20000
b100100000000000000000000 (
b100100000000000000000000 )
#30000
b110000000000000000000000 (
b110000000000000000000000 )
#40000
b110100000000000000000000 (
b110100000000000000000000 )
#50000
b10001100000000000000000000 (
b10001100000000000000000000 )
#60000
b10101100000000000000000000 (
b10101100000000000000000000 )
#70000
b10000000000000000000000 (
b10000000000000000000000 )
#80000
b1000000000000000000000 (
b1000000000000000000000 )
#90000
b11111100000000000000000000 (
b11111100000000000000000000 )
