rtl/instruction_memory.v
`timescale 1ns/1ps

module instruction_memory (
    input  wire [31:0] address,
    output reg  [31:0] instruction
);

    reg [31:0] memory [0:15];

    initial begin

        // Example instructions
        memory[0]  = 32'h00000001;
        memory[1]  = 32'h00000002;
        memory[2]  = 32'h00000003;
        memory[3]  = 32'h00000004;
        memory[4]  = 32'h00000005;
        memory[5]  = 32'h00000006;
        memory[6]  = 32'h00000007;
        memory[7]  = 32'h00000008;
        memory[8]  = 32'h00000009;
        memory[9]  = 32'h0000000A;
        memory[10] = 32'h0000000B;
        memory[11] = 32'h0000000C;
        memory[12] = 32'h0000000D;
        memory[13] = 32'h0000000E;
        memory[14] = 32'h0000000F;
        memory[15] = 32'h00000010;

    end

    always @(*) begin

        // Address is byte address.
        // Divide by 4 to get instruction index.

        if (address < 32'd64)
            instruction = memory[address[5:2]];
        else
            instruction = 32'h00000000;

    end

endmodule

tb/instruction_memory_tb.v
`timescale 1ns/1ps

module instruction_memory_tb;

    reg [31:0] address;
    wire [31:0] instruction;

    // Instantiate Instruction Memory
    instruction_memory uut (
        .address(address),
        .instruction(instruction)
    );

    initial begin

        // Create waveform
        $dumpfile("instruction_memory_waveform.vcd");
        $dumpvars(0, instruction_memory_tb);

        $monitor(
            "Time=%0t | Address=%d | Instruction=%h",
            $time,
            address,
            instruction
        );

        // =========================
        // Instruction 0
        // =========================

        address = 32'd0;
        #10;

        // =========================
        // Instruction 1
        // =========================

        address = 32'd4;
        #10;

        // =========================
        // Instruction 2
        // =========================

        address = 32'd8;
        #10;

        // =========================
        // Instruction 3
        // =========================

        address = 32'd12;
        #10;

        // =========================
        // Instruction 4
        // =========================

        address = 32'd16;
        #10;

        // =========================
        // Instruction 5
        // =========================

        address = 32'd20;
        #10;

        // =========================
        // Instruction 10
        // =========================

        address = 32'd40;
        #10;

        // =========================
        // Invalid address
        // =========================

        address = 32'd100;
        #10;

        $finish;

    end

endmodule

tb/instruction_memory_waveform.vcd
$date
	Sun Aug 30 10:17:57 2026
$end
$version
	Icarus Verilog
$end
$timescale
	1ps
$end
$scope module instruction_memory_tb $end
$var wire 32 ! instruction [31:0] $end
$var reg 32 " address [31:0] $end
$scope module uut $end
$var wire 32 # address [31:0] $end
$var reg 32 $ instruction [31:0] $end
$upscope $end
$upscope $end
$enddefinitions $end
$comment Show the parameter values. $end
$dumpall
$end
#0
$dumpvars
b1 $
b0 #
b0 "
b1 !
$end
#10000
b10 !
b10 $
b100 "
b100 #
#20000
b11 !
b11 $
b1000 "
b1000 #
#30000
b100 !
b100 $
b1100 "
b1100 #
#40000
b101 !
b101 $
b10000 "
b10000 #
#50000
b110 !
b110 $
b10100 "
b10100 #
#60000
b1011 !
b1011 $
b101000 "
b101000 #
#70000
b0 !
b0 $
b1100100 "
b1100100 #
