rtl/program_counter.v
`timescale 1ns/1ps

module program_counter (
    input  wire        clk,
    input  wire        reset,
    input  wire        enable,
    input  wire        load,
    input  wire [31:0] load_address,

    output reg  [31:0] pc
);

always @(posedge clk or posedge reset) begin

    if (reset) begin
        pc <= 32'd0;
    end

    else if (load) begin
        pc <= load_address;
    end

    else if (enable) begin
        pc <= pc + 32'd4;
    end

end

endmodule

tb/program_counter_tb.v
`timescale 1ns/1ps

module program_counter_tb;

    reg clk;
    reg reset;
    reg enable;
    reg load;

    reg [31:0] load_address;

    wire [31:0] pc;


    // =====================================
    // Instantiate Program Counter
    // =====================================

    program_counter uut (
        .clk(clk),
        .reset(reset),
        .enable(enable),
        .load(load),
        .load_address(load_address),
        .pc(pc)
    );


    // =====================================
    // Clock Generation
    // =====================================

    initial begin
        clk = 1'b0;

        forever #5 clk = ~clk;
    end


    // =====================================
    // Testbench
    // =====================================

    initial begin

        // Create waveform
        $dumpfile("program_counter_waveform.vcd");
        $dumpvars(0, program_counter_tb);
$monitor(
    "Time=%0t | Reset=%b | Enable=%b | Load=%b | Load_Address=%d | PC=%d",
    $time, reset, enable, load, load_address, pc
);

        // Initial values
        reset = 1'b1;
        enable = 1'b0;
        load = 1'b0;
        load_address = 32'd0;

        #10;


        // =================================
        // Release Reset
        // PC should be 0
        // =================================

        reset = 1'b0;
        enable = 1'b1;

        #10;


        // =================================
        // PC increments
        // 0 -> 4
        // =================================

        #10;


        // =================================
        // PC increments
        // 4 -> 8
        // =================================

        #10;


        // =================================
        // PC increments
        // 8 -> 12
        // =================================

        #10;


        // =================================
        // LOAD ADDRESS
        // PC = 100
        // =================================

        load = 1'b1;
        enable = 1'b0;
        load_address = 32'd100;

        #10;


        // =================================
        // Continue incrementing
        // 100 -> 104
        // =================================

        load = 1'b0;
        enable = 1'b1;

        #10;


        // =================================
        // 104 -> 108
        // =================================

        #10;


        // =================================
        // HOLD PC
        // =================================

        enable = 1'b0;

        #20;


        // =================================
        // RESET
        // PC should return to 0
        // =================================

        reset = 1'b1;

        #10;

        reset = 1'b0;

        #10;


        $finish;

    end

endmodule

tb/program_counter_waveform.vcd
$date
	Sat Aug 29 11:06:53 2026
$end
$version
	Icarus Verilog
$end
$timescale
	1ps
$end
$scope module program_counter_tb $end
$var wire 32 ! pc [31:0] $end
$var reg 1 " clk $end
$var reg 1 # enable $end
$var reg 1 $ load $end
$var reg 32 % load_address [31:0] $end
$var reg 1 & reset $end
$scope module uut $end
$var wire 1 " clk $end
$var wire 1 # enable $end
$var wire 1 $ load $end
$var wire 32 ' load_address [31:0] $end
$var wire 1 & reset $end
$var reg 32 ( pc [31:0] $end
$upscope $end
$upscope $end
$enddefinitions $end
$comment Show the parameter values. $end
$dumpall
$end
#0
$dumpvars
b0 (
b0 '
1&
b0 %
0$
0#
0"
b0 !
$end
#5000
1"
#10000
0"
1#
0&
#15000
b100 !
b100 (
1"
#20000
0"
#25000
b1000 !
b1000 (
1"
#30000
0"
#35000
b1100 !
b1100 (
1"
#40000
0"
#45000
b10000 !
b10000 (
1"
#50000
0"
b1100100 %
b1100100 '
0#
1$
#55000
b1100100 !
b1100100 (
1"
#60000
0"
1#
0$
#65000
b1101000 !
b1101000 (
1"
#70000
0"
#75000
b1101100 !
b1101100 (
1"
#80000
0"
0#
#85000
1"
#90000
0"
#95000
1"
#100000
b0 !
b0 (
0"
1&
#105000
1"
#110000
0"
0&
