rtl/register_file.v
`timescale 1ns/1ps

module register_file (
    input wire clk,
    input wire reset,
    input wire we,

    input wire [2:0] write_addr,
    input wire [2:0] read_addr1,
    input wire [2:0] read_addr2,

    input wire [7:0] write_data,

    output wire [7:0] read_data1,
    output wire [7:0] read_data2
);

    // 8 registers, each 8 bits
    reg [7:0] registers [0:7];

    integer i;

    // Write operation
    always @(posedge clk or posedge reset) begin
        if (reset) begin
            for (i = 0; i < 8; i = i + 1) begin
                registers[i] <= 8'b00000000;
            end
        end
        else if (we) begin
            registers[write_addr] <= write_data;
        end
    end

    // Read operation
    assign read_data1 = registers[read_addr1];
    assign read_data2 = registers[read_addr2];

endmodule

tb/register_file_tb.v
`timescale 1ns/1ps

module register_file_tb;

    reg clk;
    reg reset;
    reg we;

    reg [2:0] write_addr;
    reg [2:0] read_addr1;
    reg [2:0] read_addr2;

    reg [7:0] write_data;

    wire [7:0] read_data1;
    wire [7:0] read_data2;


    // Instantiate Register File
    register_file uut (
        .clk(clk),
        .reset(reset),
        .we(we),

        .write_addr(write_addr),
        .read_addr1(read_addr1),
        .read_addr2(read_addr2),

        .write_data(write_data),

        .read_data1(read_data1),
        .read_data2(read_data2)
    );


    // Clock generation
    initial begin
        clk = 0;

        forever #5 clk = ~clk;
    end


    // Test cases
    initial begin

        // Generate waveform
        $dumpfile("register_file_waveform.vcd");
        $dumpvars(0, register_file_tb);


        // Initial values
        reset = 1;
        we = 0;

        write_addr = 3'b000;
        read_addr1 = 3'b000;
        read_addr2 = 3'b000;

        write_data = 8'b00000000;

        #10;

        // Release reset
        reset = 0;


        // ============================
        // Write 10 into Register R1
        // ============================

        we = 1;
        write_addr = 3'b001;
        write_data = 8'd10;

        #10;


        // ============================
        // Write 20 into Register R2
        // ============================

        write_addr = 3'b010;
        write_data = 8'd20;

        #10;


        // ============================
        // Write 30 into Register R3
        // ============================

        write_addr = 3'b011;
        write_data = 8'd30;

        #10;


        // Disable writing
        we = 0;


        // ============================
        // Read R1 and R2
        // Expected:
        // read_data1 = 10
        // read_data2 = 20
        // ============================

        read_addr1 = 3'b001;
        read_addr2 = 3'b010;

        #10;


        // ============================
        // Read R2 and R3
        // Expected:
        // read_data1 = 20
        // read_data2 = 30
        // ============================

        read_addr1 = 3'b010;
        read_addr2 = 3'b011;

        #10;


        // ============================
        // Read R1 and R3
        // Expected:
        // read_data1 = 10
        // read_data2 = 30
        // ============================

        read_addr1 = 3'b001;
        read_addr2 = 3'b011;

        #20;

        $finish;

    end

endmodule

tb/register_file_waveform.vcd
$date
	Fri Aug 28 20:54:10 2026
$end
$version
	Icarus Verilog
$end
$timescale
	1ps
$end
$scope module register_file_tb $end
$var wire 8 ! read_data2 [7:0] $end
$var wire 8 " read_data1 [7:0] $end
$var reg 1 # clk $end
$var reg 3 $ read_addr1 [2:0] $end
$var reg 3 % read_addr2 [2:0] $end
$var reg 1 & reset $end
$var reg 1 ' we $end
$var reg 3 ( write_addr [2:0] $end
$var reg 8 ) write_data [7:0] $end
$scope module uut $end
$var wire 1 # clk $end
$var wire 3 * read_addr1 [2:0] $end
$var wire 3 + read_addr2 [2:0] $end
$var wire 8 , read_data1 [7:0] $end
$var wire 8 - read_data2 [7:0] $end
$var wire 1 & reset $end
$var wire 1 ' we $end
$var wire 3 . write_addr [2:0] $end
$var wire 8 / write_data [7:0] $end
$var integer 32 0 i [31:0] $end
$upscope $end
$upscope $end
$enddefinitions $end
$comment Show the parameter values. $end
$dumpall
$end
#0
$dumpvars
b1000 0
b0 /
b0 .
b0 -
b0 ,
b0 +
b0 *
b0 )
b0 (
0'
1&
b0 %
b0 $
0#
b0 "
b0 !
$end
#5000
b1000 0
1#
#10000
0#
b1010 )
b1010 /
b1 (
b1 .
1'
0&
#15000
1#
#20000
0#
b10100 )
b10100 /
b10 (
b10 .
#25000
1#
#30000
0#
b11110 )
b11110 /
b11 (
b11 .
#35000
1#
#40000
0#
b10100 !
b10100 -
b10 %
b10 +
b1010 "
b1010 ,
b1 $
b1 *
0'
#45000
1#
#50000
0#
b11110 !
b11110 -
b11 %
b11 +
b10100 "
b10100 ,
b10 $
b10 *
#55000
1#
#60000
0#
b1010 "
b1010 ,
b1 $
b1 *
